Metadata-Version: 2.1
Name: algoisto
Version: 0.4
Summary: A lot of collection
Home-page: UNKNOWN
Author: K.A.ISHAN OSHADA
Author-email: <ic31908@gmail.com>
License: UNKNOWN
Keywords: more
Platform: UNKNOWN
Classifier: Development Status :: 1 - Planning
Classifier: Intended Audience :: Developers
Classifier: Programming Language :: Python :: 3
Classifier: Operating System :: Unix
Classifier: Operating System :: MacOS :: MacOS X
Classifier: Operating System :: Microsoft :: Windows
